{
	"animations": [
		{
			"offsets": [
				0,
				11
			],
			"indices": [],
			"fps": 24,
			"anim": "idle",
			"loop": false,
			"name": "spike_idle"
		},
		{
			"offsets": [
				5,
				-5
			],
			"indices": [],
			"fps": 24,
			"anim": "singLEFT",
			"loop": false,
			"name": "spike_left"
		},
		{
			"offsets": [
				-15,
				-15
			],
			"indices": [],
			"fps": 24,
			"anim": "singDOWN",
			"loop": false,
			"name": "spike_down"
		},
		{
			"offsets": [
				-40,
				33
			],
			"indices": [],
			"fps": 24,
			"anim": "singUP",
			"loop": false,
			"name": "spike_up"
		},
		{
			"offsets": [
				-50,
				3
			],
			"indices": [],
			"fps": 24,
			"anim": "singRIGHT",
			"loop": false,
			"name": "spike_right"
		}
	],
	"no_antialiasing": false,
	"image": "characters/realSpikeJake",
	"position": [
		-270,
		130
	],
	"healthicon": "realJake",
	"flip_x": false,
	"healthbar_colors": [
		161,
		161,
		161
	],
	"camera_position": [
		30,
		0
	],
	"sing_duration": 6.1,
	"scale": 1
}